kitdo/__init__.py
kitdo/__main__.py
kitdo/manifestTb.py
kitodoo/__init__.py
kitodoo/__main__.py
kitodoo/manifestTb.py
kitdo-0.0.1.dist-info/LICENSE
kitdo-0.0.1.dist-info/METADATA
kitdo-0.0.1.dist-info/WHEEL
kitdo-0.0.1.dist-info/entry_points.txt
kitdo-0.0.1.dist-info/top_level.txt
kitdo-0.0.1.dist-info/RECORD
